happy_control/Lie_tools.py
happy_control/__init__.py
happy_control/approximation_tools.py
happy_control/shuffle_tools.py
happy_control/fliess/lie_basis.pickle
happy_control/fliess/moments_grading.pickle
happy_control/nonlinear_moments/lie_basis.pickle
happy_control/nonlinear_moments/moments_grading.pickle
happy_control-0.1.1.dist-info/LICENSE
happy_control-0.1.1.dist-info/METADATA
happy_control-0.1.1.dist-info/WHEEL
happy_control-0.1.1.dist-info/top_level.txt
happy_control-0.1.1.dist-info/RECORD
