Metadata-Version: 2.1
Name: happy-control
Version: 0.1.1
Summary: Nonlinear Algebraic Approximation in Control systems
Home-page: https://github.com/ViktorRusakov/happy-control
Author: Viktor Rusakov
Author-email: vrusakov66@gmail.com
License: UNKNOWN
Platform: UNKNOWN
Classifier: Programming Language :: Python :: 3
Classifier: License :: OSI Approved :: MIT License
Classifier: Operating System :: OS Independent
Requires-Python: >=3.6
License-File: LICENSE
Requires-Dist: antlr4-python3-runtime (>=4.8)
Requires-Dist: Cython (>=0.29.14)
Requires-Dist: numpy (>=1.18.1)
Requires-Dist: sympy (>=1.5.1)
